{"cameraMode":{"drawMode":0,"name":"Shaded","section":"Shading Mode"},"sceneLighting":true,"audioPlay":false,"sceneViewState":{"m_AlwaysRefresh":false,"showFog":true,"showSkybox":true,"showFlares":true,"showImageEffects":true,"showParticleSystems":true,"showVisualEffectGraphs":true,"m_FxEnabled":true},"in2DMode":false,"pivot":{"x":-7.341058254241943,"y":-0.8548594117164612,"z":-2.57344651222229},"rotation":{"x":-0.0783359631896019,"y":0.8819172382354736,"z":-0.1580321192741394,"w":-0.4371636211872101},"size":6.567337512969971,"orthographic":false}